[
  {
    "project_id": "113355",
    "image": "./assets/projects/mytube.png",
    "project_name": "My Tube",
    "project_description": "This website kind of similar to YouTube. I've included a search feature for this website so visitors may use the search bar to find the information they need",
    "technology": [
      "React JS",
      "React Player",
      "React Router Dom",
      "Material UI",
      "Axios"
    ],
    "client_side_repo": "https://github.com/towhidulislamalif/my-tube",
    "live_site_link": "https://my-tube-200.netlify.app/"
  },
  {
    "project_id": "224466",
    "image": "./assets/projects/servicereview.png",
    "project_name": "Personal Online Trainer",
    "project_description": "This website offers personal online fitness training and gives the best fitness advice",
    "technology": [
      "React JS",
      "Node JS",
      ", Express JS",
      "MongoDB",
      "Firebase",
      "JSONWEBTOKEN"
    ],
    "client_side_repo": "https://github.com/towhidulislamalif/service-review-client-side",
    "server_side_repo": "https://github.com/towhidulislamalif/service-review-server-side",
    "live_site_link": "https://service-review-2a095.web.app/"
  },
  {
    "project_id": "336699",
    "image": "./assets/projects/codecamp.png",
    "project_name": "CODE CAMP",
    "project_description": "Code Camp is a platform for learning where students can learn new things",
    "technology": [
      "React JS",
      "Node JS",
      ", Express JS",
      "MongoDB",
      "Firebase"
    ],
    "client_side_repo": "https://github.com/towhidulislamalif/code-camp-client",
    "server_side_repo": "https://github.com/towhidulislamalif/code-camp-sever",
    "live_site_link": "https://codecamp-8f4e0.web.app/"
  },
  {
    "project_id": "448812",
    "image": "./assets/projects/game.png",
    "project_name": "Rock Paper Scissors Game",
    "project_description": "Fully responsive Rock Scissors Game",
    "technology": ["HTML", "CSS", ", JavaScript"],
    "client_side_repo": "https://github.com/towhidulislamalif/rock-paper-scissors-game",
    "live_site_link": "https://rock-paper-scissors-master-game.netlify.app/"
  }
]
